{
  "tables": {
    "active_landing_pages": [
      {
        "column": "id",
        "type": "uuid",
        "nullable": "YES",
        "default": null
      },
      {
        "column": "business_id",
        "type": "uuid",
        "nullable": "YES",
        "default": null
      },
      {
        "column": "template_id",
        "type": "text",
        "nullable": "YES",
        "default": null
      },
      {
        "column": "content_json",
        "type": "jsonb",
        "nullable": "YES",
        "default": null
      },
      {
        "column": "is_published",
        "type": "boolean",
        "nullable": "YES",
        "default": null
      },
      {
        "column": "page_status",
        "type": "text",
        "nullable": "YES",
        "default": null
      },
      {
        "column": "business_name",
        "type": "text",
        "nullable": "YES",
        "default": null
      },
      {
        "column": "business_slug",
        "type": "text",
        "nullable": "YES",
        "default": null
      },
      {
        "column": "category",
        "type": "text",
        "nullable": "YES",
        "default": null
      },
      {
        "column": "zalo_phone",
        "type": "text",
        "nullable": "YES",
        "default": null
      },
      {
        "column": "hotline",
        "type": "text",
        "nullable": "YES",
        "default": null
      },
      {
        "column": "logo_url",
        "type": "text",
        "nullable": "YES",
        "default": null
      },
      {
        "column": "is_verified",
        "type": "boolean",
        "nullable": "YES",
        "default": null
      },
      {
        "column": "subscription_status",
        "type": "text",
        "nullable": "YES",
        "default": null
      },
      {
        "column": "expiry_date",
        "type": "timestamp with time zone",
        "nullable": "YES",
        "default": null
      }
    ],
    "analytics_events": [
      {
        "column": "id",
        "type": "uuid",
        "nullable": "NO",
        "default": "gen_random_uuid()"
      },
      {
        "column": "business_id",
        "type": "uuid",
        "nullable": "YES",
        "default": null
      },
      {
        "column": "event_type",
        "type": "text",
        "nullable": "YES",
        "default": null
      },
      {
        "column": "page_slug",
        "type": "text",
        "nullable": "YES",
        "default": null
      },
      {
        "column": "created_at",
        "type": "timestamp with time zone",
        "nullable": "YES",
        "default": "now()"
      }
    ],
    "blogs": [
      {
        "column": "id",
        "type": "uuid",
        "nullable": "NO",
        "default": "gen_random_uuid()"
      },
      {
        "column": "business_id",
        "type": "uuid",
        "nullable": "NO",
        "default": null
      },
      {
        "column": "title",
        "type": "text",
        "nullable": "NO",
        "default": null
      },
      {
        "column": "content",
        "type": "text",
        "nullable": "NO",
        "default": null
      },
      {
        "column": "image_url",
        "type": "text",
        "nullable": "YES",
        "default": null
      },
      {
        "column": "status",
        "type": "text",
        "nullable": "YES",
        "default": "'Published'::text"
      },
      {
        "column": "created_at",
        "type": "timestamp with time zone",
        "nullable": "YES",
        "default": "now()"
      },
      {
        "column": "updated_at",
        "type": "timestamp with time zone",
        "nullable": "YES",
        "default": "now()"
      }
    ],
    "bookings": [
      {
        "column": "id",
        "type": "uuid",
        "nullable": "NO",
        "default": "uuid_generate_v4()"
      },
      {
        "column": "business_id",
        "type": "uuid",
        "nullable": "NO",
        "default": null
      },
      {
        "column": "customer_info",
        "type": "jsonb",
        "nullable": "NO",
        "default": null
      },
      {
        "column": "status",
        "type": "text",
        "nullable": "NO",
        "default": "'new'::text"
      },
      {
        "column": "source_url",
        "type": "text",
        "nullable": "YES",
        "default": null
      },
      {
        "column": "created_at",
        "type": "timestamp with time zone",
        "nullable": "NO",
        "default": "timezone('utc'::text, now())"
      }
    ],
    "business_locations": [
      {
        "column": "id",
        "type": "uuid",
        "nullable": "NO",
        "default": "uuid_generate_v4()"
      },
      {
        "column": "business_id",
        "type": "uuid",
        "nullable": "NO",
        "default": null
      },
      {
        "column": "city",
        "type": "text",
        "nullable": "NO",
        "default": "'TP.HCM'::text"
      },
      {
        "column": "district",
        "type": "text",
        "nullable": "NO",
        "default": null
      },
      {
        "column": "address_full",
        "type": "text",
        "nullable": "NO",
        "default": null
      },
      {
        "column": "lat",
        "type": "double precision",
        "nullable": "YES",
        "default": null
      },
      {
        "column": "lng",
        "type": "double precision",
        "nullable": "YES",
        "default": null
      }
    ],
    "business_profiles": [
      {
        "column": "id",
        "type": "uuid",
        "nullable": "NO",
        "default": "uuid_generate_v4()"
      },
      {
        "column": "account_id",
        "type": "uuid",
        "nullable": "NO",
        "default": null
      },
      {
        "column": "business_name",
        "type": "text",
        "nullable": "NO",
        "default": null
      },
      {
        "column": "slug",
        "type": "text",
        "nullable": "NO",
        "default": null
      },
      {
        "column": "category",
        "type": "text",
        "nullable": "NO",
        "default": null
      },
      {
        "column": "zalo_phone",
        "type": "text",
        "nullable": "YES",
        "default": null
      },
      {
        "column": "hotline",
        "type": "text",
        "nullable": "YES",
        "default": null
      },
      {
        "column": "logo_url",
        "type": "text",
        "nullable": "YES",
        "default": null
      },
      {
        "column": "is_verified",
        "type": "boolean",
        "nullable": "NO",
        "default": "false"
      },
      {
        "column": "created_at",
        "type": "timestamp with time zone",
        "nullable": "NO",
        "default": "timezone('utc'::text, now())"
      },
      {
        "column": "location_city",
        "type": "text",
        "nullable": "YES",
        "default": "''::text"
      },
      {
        "column": "location_district",
        "type": "text",
        "nullable": "YES",
        "default": "''::text"
      },
      {
        "column": "rating_score",
        "type": "double precision",
        "nullable": "YES",
        "default": "5.0"
      },
      {
        "column": "social_links",
        "type": "jsonb",
        "nullable": "YES",
        "default": "'{}'::jsonb"
      }
    ],
    "landing_pages": [
      {
        "column": "id",
        "type": "uuid",
        "nullable": "NO",
        "default": "uuid_generate_v4()"
      },
      {
        "column": "business_id",
        "type": "uuid",
        "nullable": "NO",
        "default": null
      },
      {
        "column": "template_id",
        "type": "text",
        "nullable": "NO",
        "default": "'royal'::text"
      },
      {
        "column": "content_json",
        "type": "jsonb",
        "nullable": "NO",
        "default": "'{}'::jsonb"
      },
      {
        "column": "is_published",
        "type": "boolean",
        "nullable": "NO",
        "default": "false"
      },
      {
        "column": "updated_at",
        "type": "timestamp with time zone",
        "nullable": "NO",
        "default": "timezone('utc'::text, now())"
      },
      {
        "column": "status",
        "type": "text",
        "nullable": "YES",
        "default": "'Draft'::text"
      },
      {
        "column": "draft_json",
        "type": "jsonb",
        "nullable": "YES",
        "default": null
      }
    ],
    "notifications": [
      {
        "column": "id",
        "type": "uuid",
        "nullable": "NO",
        "default": "gen_random_uuid()"
      },
      {
        "column": "recipient_id",
        "type": "uuid",
        "nullable": "YES",
        "default": null
      },
      {
        "column": "type",
        "type": "text",
        "nullable": "YES",
        "default": null
      },
      {
        "column": "title",
        "type": "text",
        "nullable": "YES",
        "default": null
      },
      {
        "column": "message",
        "type": "text",
        "nullable": "YES",
        "default": null
      },
      {
        "column": "is_read",
        "type": "boolean",
        "nullable": "YES",
        "default": "false"
      },
      {
        "column": "created_at",
        "type": "timestamp with time zone",
        "nullable": "YES",
        "default": "now()"
      }
    ],
    "packages": [
      {
        "column": "id",
        "type": "uuid",
        "nullable": "NO",
        "default": "gen_random_uuid()"
      },
      {
        "column": "name",
        "type": "text",
        "nullable": "NO",
        "default": null
      },
      {
        "column": "price",
        "type": "numeric",
        "nullable": "NO",
        "default": null
      },
      {
        "column": "trial_days",
        "type": "integer",
        "nullable": "YES",
        "default": "0"
      },
      {
        "column": "duration_days",
        "type": "integer",
        "nullable": "YES",
        "default": "365"
      },
      {
        "column": "features",
        "type": "jsonb",
        "nullable": "YES",
        "default": "'[]'::jsonb"
      },
      {
        "column": "created_at",
        "type": "timestamp with time zone",
        "nullable": "YES",
        "default": "now()"
      }
    ],
    "profiles": [
      {
        "column": "id",
        "type": "uuid",
        "nullable": "NO",
        "default": null
      },
      {
        "column": "role",
        "type": "text",
        "nullable": "NO",
        "default": "'business'::text"
      },
      {
        "column": "full_name",
        "type": "text",
        "nullable": "YES",
        "default": null
      },
      {
        "column": "email",
        "type": "text",
        "nullable": "NO",
        "default": null
      },
      {
        "column": "subscription_status",
        "type": "text",
        "nullable": "NO",
        "default": "'trial'::text"
      },
      {
        "column": "expiry_date",
        "type": "timestamp with time zone",
        "nullable": "NO",
        "default": "(now() + '30 days'::interval)"
      },
      {
        "column": "created_at",
        "type": "timestamp with time zone",
        "nullable": "NO",
        "default": "timezone('utc'::text, now())"
      }
    ],
    "reviews": [
      {
        "column": "id",
        "type": "uuid",
        "nullable": "NO",
        "default": "uuid_generate_v4()"
      },
      {
        "column": "business_id",
        "type": "uuid",
        "nullable": "NO",
        "default": null
      },
      {
        "column": "author_name",
        "type": "text",
        "nullable": "NO",
        "default": null
      },
      {
        "column": "rating",
        "type": "integer",
        "nullable": "NO",
        "default": null
      },
      {
        "column": "comment",
        "type": "text",
        "nullable": "YES",
        "default": null
      },
      {
        "column": "created_at",
        "type": "timestamp with time zone",
        "nullable": "NO",
        "default": "timezone('utc'::text, now())"
      }
    ],
    "subscriptions": [
      {
        "column": "id",
        "type": "uuid",
        "nullable": "NO",
        "default": "gen_random_uuid()"
      },
      {
        "column": "business_id",
        "type": "uuid",
        "nullable": "NO",
        "default": null
      },
      {
        "column": "package_id",
        "type": "uuid",
        "nullable": "NO",
        "default": null
      },
      {
        "column": "status",
        "type": "text",
        "nullable": "YES",
        "default": "'Pending'::text"
      },
      {
        "column": "start_date",
        "type": "timestamp with time zone",
        "nullable": "YES",
        "default": "now()"
      },
      {
        "column": "end_date",
        "type": "timestamp with time zone",
        "nullable": "YES",
        "default": null
      },
      {
        "column": "created_at",
        "type": "timestamp with time zone",
        "nullable": "YES",
        "default": "now()"
      },
      {
        "column": "verified",
        "type": "boolean",
        "nullable": "YES",
        "default": "false"
      }
    ]
  },
  "enums": {
    "booking_status": [
      "Pending",
      "Confirmed",
      "Completed",
      "Cancelled"
    ],
    "business_category": [
      "Spa",
      "Dental",
      "Clinic",
      "Beauty"
    ],
    "page_status": [
      "Draft",
      "Published"
    ],
    "user_role": [
      "Admin",
      "Business"
    ]
  }
}